taqy/__init__.py
taqy/usequity.py
taqy/utils.py
taqy-0.42.4.dist-info/LICENSE
taqy-0.42.4.dist-info/METADATA
taqy-0.42.4.dist-info/WHEEL
taqy-0.42.4.dist-info/RECORD
