Metadata-Version: 2.3
Name: taqy
Version: 0.42.4
Summary: Efficient queries of trade and book data in bars. Supports the WRDS TAQ millisecond database.
License: GPL-3.0-or-later
Keywords: WRDS,TAQ,equity,market
Author: Brian K. Boonstra
Author-email: software@boonstra.org
Requires-Python: >=3.10
Classifier: Development Status :: 4 - Beta
Classifier: Intended Audience :: Developers
Classifier: Intended Audience :: Financial and Insurance Industry
Classifier: Topic :: Database
Classifier: Topic :: Office/Business :: Financial :: Investment
Provides-Extra: dev
Provides-Extra: parquet-fastparquet
Provides-Extra: parquet-pyarrow
Requires-Dist: black ; extra == "dev"
Requires-Dist: fastparquet (>=0.8) ; extra == "parquet-fastparquet"
Requires-Dist: flake8 ; extra == "dev"
Requires-Dist: pandas (>=2.2.3,<3.0.0)
Requires-Dist: pyarrow (>=11.0.0) ; extra == "parquet-pyarrow"
Requires-Dist: pytz (>=2025.2,<2026.0)
Requires-Dist: wrds (>=3.3.0,<4.0.0)
